{
  "name": "inst_shift_logical_right_64_with_overflow",
  "initial-regs": [
    0,
    0,
    0,
    0,
    0,
    0,
    0,
    9223372036854775925,
    65,
    0,
    0,
    0,
    0
  ],
  "initial-pc": 0,
  "initial-page-map": [],
  "initial-memory": [],
  "initial-gas": 10000,
  "program": [
    0,
    0,
    3,
    208,
    135,
    9,
    1
  ],
  "expected-status": "panic",
  "expected-regs": [
    0,
    0,
    0,
    0,
    0,
    0,
    0,
    9223372036854775925,
    65,
    4611686018427387962,
    0,
    0,
    0
  ],
  "expected-pc": 3,
  "expected-memory": [],
  "expected-gas": 9998
}